{
  "id": "java_foundation_008",
  "title": "Arrays in Java",
  "difficulty": "Beginner",
  "estimatedMinutes": 65,

  "content": {
    "topic_intro": {
      "text": "Arrays are used to store multiple values of the same datatype inside a single variable. Instead of creating many separate variables, arrays help organize large amounts of data efficiently."
    },

    "why_learn_this": [
      "Arrays help store multiple values together",
      "Arrays reduce the need for hundreds of variables",
      "Games, apps, and websites use arrays everywhere",
      "Arrays are important for loops and data processing",
      "Arrays are the foundation for advanced data structures"
    ],

    "explanations": [
      {
        "type": "simple",
        "text": "An array stores multiple values together."
      },

      {
        "type": "real_life",
        "text": "An array is like a row of lockers where each locker stores one item."
      },

      {
        "type": "student_friendly",
        "text": "Instead of marks1, marks2, marks3, arrays help store all marks in one variable."
      },

      {
        "type": "technical",
        "text": "Arrays are fixed-size data structures storing same datatype values in contiguous memory locations."
      },

      {
        "type": "deep",
        "text": "Arrays provide indexed access to sequentially stored homogeneous data for efficient storage and retrieval."
      }
    ],

    "basic_terms": [
      {
        "term": "Array",
        "meaning": "A collection of multiple values."
      },

      {
        "term": "Index",
        "meaning": "Position number of an element."
      },

      {
        "term": "Element",
        "meaning": "A value stored inside an array."
      },

      {
        "term": "Length",
        "meaning": "Total number of elements in array."
      },

      {
        "term": "Traversal",
        "meaning": "Accessing all elements one by one."
      }
    ],

    "array_creation": [

      {
        "method": "Direct Initialization",

        "explanations": [
          {
            "type": "simple",
            "text": "Values are directly stored while creating array."
          },

          {
            "type": "student_friendly",
            "text": "This is the easiest way to create arrays."
          },

          {
            "type": "real_life",
            "text": "Useful when values are already known."
          },

          {
            "type": "technical",
            "text": "Array memory and values are initialized together."
          },

          {
            "type": "deep",
            "text": "Direct initialization creates compact and readable array declarations."
          }
        ],

        "example": {
          "code": "int[] marks = {90, 85, 95};",

          "output": "marks array stores 90, 85, 95",

          "step_by_step": [
            "int[] creates integer array",
            "marks becomes array name",
            "3 values are stored",
            "Indexes become 0,1,2",
            "Array is ready for use"
          ]
        }
      },

      {
        "method": "Using new Keyword",

        "explanations": [
          {
            "type": "simple",
            "text": "new creates empty array with fixed size."
          },

          {
            "type": "student_friendly",
            "text": "This method creates space first and values can be added later."
          },

          {
            "type": "real_life",
            "text": "Like reserving empty lockers before storing items."
          },

          {
            "type": "technical",
            "text": "new allocates memory dynamically for array object."
          },

          {
            "type": "deep",
            "text": "Dynamic allocation helps initialize arrays when exact values are unknown initially."
          }
        ],

        "example": {
          "code": "int[] numbers = new int[5];",

          "output": "Empty array with 5 positions created",

          "step_by_step": [
            "new creates array object",
            "Array size becomes 5",
            "Indexes become 0 to 4",
            "Default values are assigned",
            "Array becomes ready for storing data"
          ]
        }
      }
    ],

    "array_examples": [

      {
        "type": "student_marks",

        "explanations": [
          {
            "type": "simple",
            "text": "Arrays can store student marks together."
          },

          {
            "type": "student_friendly",
            "text": "One array stores marks of multiple subjects."
          },

          {
            "type": "real_life",
            "text": "Schools use arrays to manage marks."
          },

          {
            "type": "technical",
            "text": "Integer arrays efficiently store numeric marks."
          },

          {
            "type": "deep",
            "text": "Arrays simplify managing academic records in education systems."
          }
        ],

        "code": "int[] marks = {90, 85, 95};",

        "output": "90 85 95",

        "step_by_step": [
          "marks array stores 3 values",
          "Each value gets index",
          "marks[0] = 90",
          "marks[1] = 85",
          "marks[2] = 95"
        ],

        "real_life": "School marks system."
      },

      {
        "type": "gaming_scores",

        "explanations": [
          {
            "type": "simple",
            "text": "Arrays can store multiple game scores."
          },

          {
            "type": "student_friendly",
            "text": "One array tracks scores of many players."
          },

          {
            "type": "real_life",
            "text": "Games use arrays for leaderboards."
          },

          {
            "type": "technical",
            "text": "Arrays organize sequential player score data."
          },

          {
            "type": "deep",
            "text": "Gaming systems rely on arrays for ranking and score management."
          }
        ],

        "code": "int[] scores = {100, 200, 150, 300};",

        "output": "100 200 150 300",

        "step_by_step": [
          "scores array stores player scores",
          "Each score gets unique index",
          "Array stores all values together",
          "Indexes allow fast access",
          "Program can display leaderboard"
        ],

        "real_life": "Gaming leaderboard."
      },

      {
        "type": "shopping_prices",

        "explanations": [
          {
            "type": "simple",
            "text": "Arrays can store multiple prices."
          },

          {
            "type": "student_friendly",
            "text": "Shopping apps use arrays for product prices."
          },

          {
            "type": "real_life",
            "text": "E-commerce apps store prices in arrays."
          },

          {
            "type": "technical",
            "text": "double[] arrays store decimal values efficiently."
          },

          {
            "type": "deep",
            "text": "Arrays help process pricing and billing systems."
          }
        ],

        "code": "double[] prices = {99.99, 150.50, 75.25};",

        "output": "99.99 150.50 75.25",

        "step_by_step": [
          "double[] stores decimal values",
          "prices array stores product prices",
          "Each value gets separate index",
          "Program can calculate totals",
          "Arrays simplify billing systems"
        ],

        "real_life": "Shopping applications."
      },

      {
        "type": "names_list",

        "explanations": [
          {
            "type": "simple",
            "text": "Arrays can store multiple names."
          },

          {
            "type": "student_friendly",
            "text": "One array can store many people names."
          },

          {
            "type": "real_life",
            "text": "Contact apps store names in arrays."
          },

          {
            "type": "technical",
            "text": "String[] arrays store text values."
          },

          {
            "type": "deep",
            "text": "Arrays help organize textual datasets efficiently."
          }
        ],

        "code": "String[] names = {\"John\", \"Alex\", \"Sam\"};",

        "output": "John Alex Sam",

        "step_by_step": [
          "String[] stores text values",
          "names array stores multiple names",
          "Each name gets unique index",
          "Array organizes data together",
          "Program can display contact list"
        ],

        "real_life": "Contact list applications."
      },

      {
        "type": "attendance_system",

        "explanations": [
          {
            "type": "simple",
            "text": "Arrays can store attendance status."
          },

          {
            "type": "student_friendly",
            "text": "Boolean arrays track present or absent students."
          },

          {
            "type": "real_life",
            "text": "Schools use attendance systems."
          },

          {
            "type": "technical",
            "text": "boolean[] arrays store true/false values."
          },

          {
            "type": "deep",
            "text": "Arrays help efficiently manage status-based datasets."
          }
        ],

        "code": "boolean[] attendance = {true, false, true};",

        "output": "true false true",

        "step_by_step": [
          "boolean[] stores true/false values",
          "attendance tracks student status",
          "Each student gets separate index",
          "true means present",
          "false means absent"
        ],

        "real_life": "School attendance systems."
      }
    ],

    "accessing_elements": {

      "title": "Accessing Array Elements",

      "explanations": [
        {
          "type": "simple",
          "text": "Indexes access array values."
        },

        {
          "type": "student_friendly",
          "text": "Each array value has position number."
        },

        {
          "type": "real_life",
          "text": "Indexes work like locker numbers."
        },

        {
          "type": "technical",
          "text": "Array indexes start from 0."
        },

        {
          "type": "deep",
          "text": "Indexed access provides fast retrieval operations."
        }
      ],

      "example": {
        "code": "int[] marks = {90, 85, 95};\n\nSystem.out.println(marks[0]);",

        "output": "90"
      },

      "step_by_step": [
        "marks[0] accesses first element",
        "Index starts from 0",
        "First value becomes 90",
        "System.out.println() prints value",
        "90 appears on screen"
      ]
    },

    "changing_values": {

      "title": "Updating Array Values",

      "explanations": [
        {
          "type": "simple",
          "text": "Array values can be changed."
        },

        {
          "type": "student_friendly",
          "text": "Indexes help replace old values."
        },

        {
          "type": "real_life",
          "text": "Marks can be updated after revaluation."
        },

        {
          "type": "technical",
          "text": "Array elements are mutable."
        },

        {
          "type": "deep",
          "text": "Indexed updates allow efficient modification operations."
        }
      ],

      "example": {
        "code": "marks[1] = 100;",

        "output": "Second element becomes 100"
      },

      "step_by_step": [
        "marks[1] accesses second element",
        "Old value becomes 85",
        "100 replaces old value",
        "Array updates successfully",
        "New value becomes stored"
      ]
    },

    "array_length": {

      "title": "Finding Array Length",

      "explanations": [
        {
          "type": "simple",
          "text": "length gives total array size."
        },

        {
          "type": "student_friendly",
          "text": "length tells how many values exist."
        },

        {
          "type": "real_life",
          "text": "Apps use length to count items."
        },

        {
          "type": "technical",
          "text": "length is built-in array property."
        },

        {
          "type": "deep",
          "text": "length supports dynamic traversal and validation operations."
        }
      ],

      "example": {
        "code": "System.out.println(marks.length);",

        "output": "3"
      }
    },

    "loops_with_arrays": {

      "title": "Using Loop with Arrays",

      "explanations": [
        {
          "type": "simple",
          "text": "Loops help print all array values."
        },

        {
          "type": "student_friendly",
          "text": "Loops remove need for repeated code."
        },

        {
          "type": "real_life",
          "text": "Apps process lists using loops."
        },

        {
          "type": "technical",
          "text": "Loops traverse arrays sequentially."
        },

        {
          "type": "deep",
          "text": "Array traversal is fundamental for algorithms and data processing."
        }
      ],

      "example": {
        "code": "int[] marks = {90, 85, 95};\n\nfor(int i = 0; i < marks.length; i++) {\n    System.out.println(marks[i]);\n}",

        "output": [
          "90",
          "85",
          "95"
        ]
      },

      "step_by_step": [
        "Loop starts from index 0",
        "Loop continues until last index",
        "marks[i] accesses each value",
        "Values print one by one",
        "All elements become displayed"
      ]
    },

    "wrong_vs_correct": [
      {
        "wrong": "int[] marks = 90, 85, 95;",
        "correct": "int[] marks = {90, 85, 95};",
        "why_wrong": "Arrays require curly braces."
      },

      {
        "wrong": "marks[3]",
        "correct": "marks[2]",
        "why_wrong": "Indexes start from 0. Last index is size - 1."
      },

      {
        "wrong": "marks.length()",
        "correct": "marks.length",
        "why_wrong": "length in arrays is property, not method."
      },

      {
        "wrong": "String[] names = {John, Alex};",
        "correct": "String[] names = {\"John\", \"Alex\"};",
        "why_wrong": "String values require double quotes."
      },

      {
        "wrong": "int[] arr = new int[-1];",
        "correct": "int[] arr = new int[5];",
        "why_wrong": "Array size cannot be negative."
      }
    ],

    "common_mistakes": [
      "Forgetting indexes start at 0",
      "Accessing invalid index",
      "Using wrong array syntax",
      "Confusing length and length()",
      "Storing different datatypes together"
    ],

    "practice": [
      "Create int array of 5 numbers.",
      "Print first and last element.",
      "Find array length.",
      "Update array value.",
      "Use loop to print all elements."
    ],

    "quiz": [
      {
        "question": "What does an array store?",
        "answer": "Multiple values"
      },

      {
        "question": "What is first array index?",
        "answer": "0"
      },

      {
        "question": "Which property gives array size?",
        "answer": "length"
      },

      {
        "question": "Can arrays store same datatype only?",
        "answer": "Yes"
      },

      {
        "question": "Which loop is commonly used with arrays?",
        "answer": "for loop"
      }
    ],

    "mini_project": {
      "title": "Student Marks Analyzer",

      "task": "Store 5 student marks in array, print all marks, find total marks, highest mark, and average."
    },

    "revision_summary": [
      "Arrays store multiple values together.",
      "Indexes start from 0.",
      "Arrays store same datatype values.",
      "length gives array size.",
      "Loops help traverse arrays.",
      "Arrays simplify large data storage."
    ]
  }
}
